drf_2fa/__init__.py
drf_2fa/admin.py
drf_2fa/apps.py
drf_2fa/exceptions.py
drf_2fa/models.py
drf_2fa/serializers.py
drf_2fa/settings.py
drf_2fa/signals.py
drf_2fa/urls.py
drf_2fa/views.py
drf_2fa/backends/__init__.py
drf_2fa/backends/authenticator.py
drf_2fa/backends/email.py
drf_2fa/backends/twilio.py
drf_2fa/migrations/0001_initial.py
drf_2fa/migrations/__init__.py
drf_2fa/templates/drf_2fa/email/message.html
drf_2fa/templates/drf_2fa/email/subject.txt
drf_2fa/templates/drf_2fa/sms/message.txt
drf_2fa-1.0.4.dist-info/LICENSE
drf_2fa-1.0.4.dist-info/METADATA
drf_2fa-1.0.4.dist-info/WHEEL
drf_2fa-1.0.4.dist-info/top_level.txt
drf_2fa-1.0.4.dist-info/RECORD
