Metadata-Version: 2.1
Name: drf-2fa
Version: 1.0.4
Summary: Integrate 2 Factor Authentication in Your Django REST API project easily.
Home-page: https://github.com/farhad0085/drf-2fa
Author: Farhad Hossain
Author-email: farhadhossain0085@gmail.com
License: MIT
Classifier: License :: OSI Approved :: MIT License
Classifier: Programming Language :: Python :: 3
Classifier: Programming Language :: Python :: 3.8
License-File: LICENSE
Requires-Dist: qrcode ==7.4.2
Requires-Dist: django >=2.2
Requires-Dist: djangorestframework >=3.14
